cans/__init__.py
cans/cli.py
cans/config.py
cans/exceptions.py
cans/py.typed
cans/validation.py
cans/api/__init__.py
cans/api/auth.py
cans/api/client.py
cans/api/mcp_server.py
cans/api/models.py
cans/api/server.py
cans/models/__init__.py
cans/models/cans.py
cans/models/cate_models.py
cans/models/gnn_modules.py
cans/pipeline/__init__.py
cans/pipeline/runner.py
cans/tutorials/TUTORIALS.md
cans/tutorials/__init__.py
cans/tutorials/tutorial_01_first_steps.py
cans/tutorials/tutorial_02_data_understanding.py
cans/tutorials/examples/sample_marketing_data.csv
cans/utils/causal.py
cans/utils/causal_assumptions.py
cans/utils/causal_evaluation.py
cans/utils/causal_losses.py
cans/utils/checkpointing.py
cans/utils/data.py
cans/utils/logging.py
cans/utils/preprocessing.py
cans/utils/uncertainty.py
cans-tutorials/__init__.py
cans-tutorials/tutorial_01_first_steps.py
cans-tutorials/tutorial_02_data_understanding.py
cans_framework-3.1.4.dist-info/licenses/LICENSE
cans_framework-3.1.4.dist-info/METADATA
cans_framework-3.1.4.dist-info/WHEEL
cans_framework-3.1.4.dist-info/entry_points.txt
cans_framework-3.1.4.dist-info/top_level.txt
cans_framework-3.1.4.dist-info/RECORD
