Metadata-Version: 2.4
Name: cans-framework
Version: 3.1.4
Summary: A production-ready deep learning framework for causal inference on structured, textual, and heterogeneous data
Home-page: https://github.com/rdmurugan/cans-framework
Author: Durai Rajamanickam
Author-email: Durai Rajamanickam <durai@infinidatum.net>
Maintainer-email: Durai Rajamanickam <durai@infinidatum.net>
License: CANS Framework Custom License
Project-URL: Homepage, https://github.com/rdmurugan/cans-framework
Project-URL: Documentation, https://github.com/rdmurugan/cans-framework#readme
Project-URL: Repository, https://github.com/rdmurugan/cans-framework
Project-URL: Bug Reports, https://github.com/rdmurugan/cans-framework/issues
Project-URL: Changelog, https://github.com/rdmurugan/cans-framework/releases
Keywords: causal-inference,deep-learning,graph-neural-networks,transformers,counterfactual,treatment-effects,machine-learning,pytorch,bert,gnn,causal-ai,econometrics,statistics
Classifier: Development Status :: 4 - Beta
Classifier: Intended Audience :: Developers
Classifier: Intended Audience :: Science/Research
Classifier: Intended Audience :: Education
Classifier: Topic :: Scientific/Engineering
Classifier: Topic :: Scientific/Engineering :: Artificial Intelligence
Classifier: Topic :: Scientific/Engineering :: Information Analysis
Classifier: Topic :: Software Development :: Libraries
Classifier: Topic :: Software Development :: Libraries :: Python Modules
Classifier: License :: Other/Proprietary License
Classifier: Programming Language :: Python :: 3
Classifier: Programming Language :: Python :: 3.8
Classifier: Programming Language :: Python :: 3.9
Classifier: Programming Language :: Python :: 3.10
Classifier: Programming Language :: Python :: 3.11
Classifier: Programming Language :: Python :: 3.12
Classifier: Operating System :: OS Independent
Classifier: Environment :: Console
Classifier: Environment :: GPU :: NVIDIA CUDA
Classifier: Natural Language :: English
Requires-Python: >=3.8
License-File: LICENSE
Requires-Dist: torch>=2.0.0
Requires-Dist: transformers>=4.38.0
Requires-Dist: torch-geometric>=2.3.0
Requires-Dist: scikit-learn>=1.3.0
Requires-Dist: pandas>=2.0.0
Requires-Dist: numpy>=1.24.0
Requires-Dist: tqdm>=4.66.0
Requires-Dist: networkx>=3.1
Requires-Dist: matplotlib>=3.7.0
Requires-Dist: seaborn>=0.12.0
Requires-Dist: plotly>=5.15.0
Requires-Dist: scipy>=1.11.0
Requires-Dist: statsmodels>=0.14.0
Requires-Dist: PyYAML>=6.0
Requires-Dist: fastapi>=0.100.0
Requires-Dist: uvicorn[standard]>=0.23.0
Requires-Dist: pydantic>=2.0.0
Requires-Dist: requests>=2.31.0
Requires-Dist: passlib[bcrypt]>=1.7.0
Requires-Dist: PyJWT>=2.8.0
Provides-Extra: dev
Requires-Dist: pytest>=7.0.0; extra == "dev"
Requires-Dist: pytest-cov>=4.0.0; extra == "dev"
Requires-Dist: pytest-mock>=3.10.0; extra == "dev"
Requires-Dist: pytest-xdist>=3.0.0; extra == "dev"
Requires-Dist: black>=22.0.0; extra == "dev"
Requires-Dist: isort>=5.10.0; extra == "dev"
Requires-Dist: flake8>=5.0.0; extra == "dev"
Requires-Dist: mypy>=0.990; extra == "dev"
Requires-Dist: pre-commit>=2.20.0; extra == "dev"
Requires-Dist: bandit>=1.7.0; extra == "dev"
Provides-Extra: api
Requires-Dist: fastapi>=0.100.0; extra == "api"
Requires-Dist: uvicorn[standard]>=0.23.0; extra == "api"
Requires-Dist: pydantic>=2.0.0; extra == "api"
Requires-Dist: requests>=2.31.0; extra == "api"
Requires-Dist: passlib[bcrypt]>=1.7.0; extra == "api"
Requires-Dist: PyJWT>=2.8.0; extra == "api"
Requires-Dist: aiohttp>=3.8.0; extra == "api"
Provides-Extra: mcp
Requires-Dist: model-context-protocol>=0.1.0; extra == "mcp"
Provides-Extra: docs
Requires-Dist: sphinx>=5.0.0; extra == "docs"
Requires-Dist: sphinx-rtd-theme>=1.0.0; extra == "docs"
Requires-Dist: sphinxcontrib-napoleon>=0.7; extra == "docs"
Requires-Dist: myst-parser>=0.18.0; extra == "docs"
Requires-Dist: sphinx-autodoc-typehints>=1.19.0; extra == "docs"
Provides-Extra: notebooks
Requires-Dist: jupyter>=1.0.0; extra == "notebooks"
Requires-Dist: jupyterlab>=3.4.0; extra == "notebooks"
Requires-Dist: ipykernel>=6.15.0; extra == "notebooks"
Requires-Dist: ipywidgets>=8.0.0; extra == "notebooks"
Requires-Dist: nbconvert>=7.0.0; extra == "notebooks"
Provides-Extra: visualization
Requires-Dist: plotly>=5.15.0; extra == "visualization"
Requires-Dist: seaborn>=0.12.0; extra == "visualization"
Requires-Dist: matplotlib>=3.7.0; extra == "visualization"
Requires-Dist: graphviz>=0.20.0; extra == "visualization"
Provides-Extra: gpu
Requires-Dist: torch>=2.0.0; extra == "gpu"
Requires-Dist: torch-geometric>=2.3.0; extra == "gpu"
Provides-Extra: all
Requires-Dist: cans-framework[dev,docs,notebooks,visualization]; extra == "all"
Dynamic: author
Dynamic: home-page
Dynamic: license-file
Dynamic: requires-python
